Metadata-Version: 2.1
Name: pybiosig
Version: 1.0.0
Summary: A python framework to work with biomedical signals.
Home-page: https://github.com/aalcaineo/PyBiosig
Author: Alejandro Alcaine, PhD
Author-email: lalcaine@usj.es
License: GNU General Public License v3.0
Keywords: Signal,Reading,Biomedical
Platform: UNKNOWN
Classifier: Development Status :: 3 - Alpha
Classifier: Intended Audience :: Developers
Classifier: Topic :: Software Development :: Build Tools
Classifier: Programming Language :: Python :: 3
License-File: LICENSE
